[{"color": [202, 4, 0], "title": "Variante 1: LaDo"}, {"color": [202, 4, 0], "title": "Variante 1: LaDo_Vision"}, {"color": [202, 4, 0], "title": "Variante 2: Achtal_Bestand"}, {"color": [202, 4, 0], "title": "Variante 2: Achtal_Bestand_Anbindung"}, {"color": [202, 4, 0], "title": "Variante 3: Achtal_P2.1"}, {"color": [202, 4, 0], "title": "Variante 3: Achtal_P2.1_Anbindung"}, {"color": [202, 4, 0], "title": "Variante 4: Buch"}, {"color": [202, 4, 0], "title": "Variante 5: BuchAchtalEgg"}, {"color": [202, 4, 0], "title": "Variante 6: Achrain"}, {"color": [202, 4, 0], "title": "Variante 7: Schwarzachtobel"}, {"color": [202, 4, 0], "title": "Variante 8:"}, {"color": [133, 182, 111], "title": ""}]